timer_demo/__main__.py
timer_demo-0.0.1.dist-info/METADATA
timer_demo-0.0.1.dist-info/WHEEL
timer_demo-0.0.1.dist-info/RECORD
